{
  "id": "01349fcd-5e1f-4f74-93f9-f58dd227e909",
  "prevId": "00000000-0000-0000-0000-000000000000",
  "version": "7",
  "dialect": "postgresql",
  "tables": {
    "public.memorials": {
      "name": "memorials",
      "schema": "",
      "columns": {
        "id": {
          "name": "id",
          "type": "uuid",
          "primaryKey": true,
          "notNull": true,
          "default": "gen_random_uuid()"
        },
        "user_id": {
          "name": "user_id",
          "type": "uuid",
          "primaryKey": false,
          "notNull": false
        },
        "name": {
          "name": "name",
          "type": "text",
          "primaryKey": false,
          "notNull": true
        },
        "profile_image": {
          "name": "profile_image",
          "type": "text",
          "primaryKey": false,
          "notNull": false
        },
        "birth_date": {
          "name": "birth_date",
          "type": "text",
          "primaryKey": false,
          "notNull": false
        },
        "death_date": {
          "name": "death_date",
          "type": "text",
          "primaryKey": false,
          "notNull": false
        },
        "location": {
          "name": "location",
          "type": "text",
          "primaryKey": false,
          "notNull": false
        },
        "obituary": {
          "name": "obituary",
          "type": "text",
          "primaryKey": false,
          "notNull": false
        },
        "timeline": {
          "name": "timeline",
          "type": "jsonb",
          "primaryKey": false,
          "notNull": false,
          "default": "'[]'::jsonb"
        },
        "favorites": {
          "name": "favorites",
          "type": "jsonb",
          "primaryKey": false,
          "notNull": false,
          "default": "'[]'::jsonb"
        },
        "family_tree": {
          "name": "family_tree",
          "type": "jsonb",
          "primaryKey": false,
          "notNull": false,
          "default": "'[]'::jsonb"
        },
        "gallery": {
          "name": "gallery",
          "type": "jsonb",
          "primaryKey": false,
          "notNull": false,
          "default": "'[]'::jsonb"
        },
        "service_info": {
          "name": "service_info",
          "type": "jsonb",
          "primaryKey": false,
          "notNull": false
        },
        "memory_wall": {
          "name": "memory_wall",
          "type": "jsonb",
          "primaryKey": false,
          "notNull": false,
          "default": "'[]'::jsonb"
        },
        "is_published": {
          "name": "is_published",
          "type": "boolean",
          "primaryKey": false,
          "notNull": false,
          "default": false
        },
        "custom_url": {
          "name": "custom_url",
          "type": "text",
          "primaryKey": false,
          "notNull": false
        },
        "theme": {
          "name": "theme",
          "type": "text",
          "primaryKey": false,
          "notNull": false,
          "default": "'default'"
        },
        "created_at": {
          "name": "created_at",
          "type": "timestamp",
          "primaryKey": false,
          "notNull": true,
          "default": "now()"
        },
        "updated_at": {
          "name": "updated_at",
          "type": "timestamp",
          "primaryKey": false,
          "notNull": true,
          "default": "now()"
        }
      },
      "indexes": {},
      "foreignKeys": {
        "memorials_user_id_users_id_fk": {
          "name": "memorials_user_id_users_id_fk",
          "tableFrom": "memorials",
          "tableTo": "users",
          "columnsFrom": [
            "user_id"
          ],
          "columnsTo": [
            "id"
          ],
          "onDelete": "cascade",
          "onUpdate": "no action"
        }
      },
      "compositePrimaryKeys": {},
      "uniqueConstraints": {
        "memorials_custom_url_unique": {
          "name": "memorials_custom_url_unique",
          "nullsNotDistinct": false,
          "columns": [
            "custom_url"
          ]
        }
      },
      "policies": {},
      "checkConstraints": {},
      "isRLSEnabled": false
    },
    "public.memories": {
      "name": "memories",
      "schema": "",
      "columns": {
        "id": {
          "name": "id",
          "type": "uuid",
          "primaryKey": true,
          "notNull": true,
          "default": "gen_random_uuid()"
        },
        "memorial_id": {
          "name": "memorial_id",
          "type": "uuid",
          "primaryKey": false,
          "notNull": false
        },
        "user_id": {
          "name": "user_id",
          "type": "uuid",
          "primaryKey": false,
          "notNull": false
        },
        "text": {
          "name": "text",
          "type": "text",
          "primaryKey": false,
          "notNull": true
        },
        "author": {
          "name": "author",
          "type": "text",
          "primaryKey": false,
          "notNull": true
        },
        "images": {
          "name": "images",
          "type": "text[]",
          "primaryKey": false,
          "notNull": false
        },
        "date": {
          "name": "date",
          "type": "timestamp",
          "primaryKey": false,
          "notNull": true,
          "default": "now()"
        },
        "created_at": {
          "name": "created_at",
          "type": "timestamp",
          "primaryKey": false,
          "notNull": true,
          "default": "now()"
        },
        "updated_at": {
          "name": "updated_at",
          "type": "timestamp",
          "primaryKey": false,
          "notNull": true,
          "default": "now()"
        }
      },
      "indexes": {},
      "foreignKeys": {
        "memories_memorial_id_memorials_id_fk": {
          "name": "memories_memorial_id_memorials_id_fk",
          "tableFrom": "memories",
          "tableTo": "memorials",
          "columnsFrom": [
            "memorial_id"
          ],
          "columnsTo": [
            "id"
          ],
          "onDelete": "cascade",
          "onUpdate": "no action"
        },
        "memories_user_id_users_id_fk": {
          "name": "memories_user_id_users_id_fk",
          "tableFrom": "memories",
          "tableTo": "users",
          "columnsFrom": [
            "user_id"
          ],
          "columnsTo": [
            "id"
          ],
          "onDelete": "cascade",
          "onUpdate": "no action"
        }
      },
      "compositePrimaryKeys": {},
      "uniqueConstraints": {},
      "policies": {},
      "checkConstraints": {},
      "isRLSEnabled": false
    },
    "public.rsvps": {
      "name": "rsvps",
      "schema": "",
      "columns": {
        "id": {
          "name": "id",
          "type": "uuid",
          "primaryKey": true,
          "notNull": true,
          "default": "gen_random_uuid()"
        },
        "memorial_id": {
          "name": "memorial_id",
          "type": "uuid",
          "primaryKey": false,
          "notNull": false
        },
        "first_name": {
          "name": "first_name",
          "type": "text",
          "primaryKey": false,
          "notNull": true
        },
        "last_name": {
          "name": "last_name",
          "type": "text",
          "primaryKey": false,
          "notNull": true
        },
        "email": {
          "name": "email",
          "type": "text",
          "primaryKey": false,
          "notNull": false
        },
        "phone": {
          "name": "phone",
          "type": "text",
          "primaryKey": false,
          "notNull": false
        },
        "attending": {
          "name": "attending",
          "type": "text",
          "primaryKey": false,
          "notNull": true
        },
        "guests": {
          "name": "guests",
          "type": "jsonb",
          "primaryKey": false,
          "notNull": false,
          "default": "'[]'::jsonb"
        },
        "created_at": {
          "name": "created_at",
          "type": "timestamp",
          "primaryKey": false,
          "notNull": true,
          "default": "now()"
        }
      },
      "indexes": {},
      "foreignKeys": {
        "rsvps_memorial_id_memorials_id_fk": {
          "name": "rsvps_memorial_id_memorials_id_fk",
          "tableFrom": "rsvps",
          "tableTo": "memorials",
          "columnsFrom": [
            "memorial_id"
          ],
          "columnsTo": [
            "id"
          ],
          "onDelete": "cascade",
          "onUpdate": "no action"
        }
      },
      "compositePrimaryKeys": {},
      "uniqueConstraints": {},
      "policies": {},
      "checkConstraints": {},
      "isRLSEnabled": false
    },
    "public.users": {
      "name": "users",
      "schema": "",
      "columns": {
        "id": {
          "name": "id",
          "type": "uuid",
          "primaryKey": true,
          "notNull": true,
          "default": "gen_random_uuid()"
        },
        "name": {
          "name": "name",
          "type": "text",
          "primaryKey": false,
          "notNull": true
        },
        "email": {
          "name": "email",
          "type": "text",
          "primaryKey": false,
          "notNull": true
        },
        "password": {
          "name": "password",
          "type": "text",
          "primaryKey": false,
          "notNull": true
        },
        "role": {
          "name": "role",
          "type": "text",
          "primaryKey": false,
          "notNull": true,
          "default": "'user'"
        },
        "is_verified": {
          "name": "is_verified",
          "type": "boolean",
          "primaryKey": false,
          "notNull": false,
          "default": false
        },
        "created_at": {
          "name": "created_at",
          "type": "timestamp",
          "primaryKey": false,
          "notNull": true,
          "default": "now()"
        },
        "updated_at": {
          "name": "updated_at",
          "type": "timestamp",
          "primaryKey": false,
          "notNull": true,
          "default": "now()"
        }
      },
      "indexes": {},
      "foreignKeys": {},
      "compositePrimaryKeys": {},
      "uniqueConstraints": {
        "users_email_unique": {
          "name": "users_email_unique",
          "nullsNotDistinct": false,
          "columns": [
            "email"
          ]
        }
      },
      "policies": {},
      "checkConstraints": {},
      "isRLSEnabled": false
    }
  },
  "enums": {},
  "schemas": {},
  "sequences": {},
  "roles": {},
  "policies": {},
  "views": {},
  "_meta": {
    "columns": {},
    "schemas": {},
    "tables": {}
  }
}